actsegextract/__init__.py
actsegextract/__version__.py
actsegextract/segment_extract.py
actsegextract-0.0.3.dist-info/METADATA
actsegextract-0.0.3.dist-info/WHEEL
actsegextract-0.0.3.dist-info/top_level.txt
actsegextract-0.0.3.dist-info/RECORD
