Metadata-Version: 2.1
Name: actsegextract
Version: 0.0.3
Summary: segid extracting tool for team act
Home-page: https://github.com/SunkyeongLee/aanlayticsact_segExtract
Author: Sunkyeong Lee
Author-email: sunkyeong.lee@concentrix.com  
Classifier: Programming Language :: Python :: 3
Classifier: License :: OSI Approved :: MIT License
Classifier: Operating System :: OS Independent
Requires-Python: >=3.6
